{
  "uid": 100033,
  "name": "HDX Chrome Finish Commercial Wire Shelving - 6 Tier",
  "description": "This easy-to-assemble Decorative Wire Chrome Finish Commercial Shelving Unit from HDX provides storage space for any room and purpose including commercial, industrial and residential use. The 6-tier shelving unit is made of tubular steel and wires coated with a durable chrome finish. All shelf heights are easily adjustable, and the unit can be assembled without any tools. Each shelf holds up to 600 lbs. when evenly distributed and features a total unit weight capacity of 3600 lbs. for optimal use in kitchens, pantries, utility rooms, warehouses and garages.Each shelf supports 600 lbs. when evenly distributed; total unit weight capacity is 3600 lbs.No tools required for easy assemblyTubular steel construction with durable chrome finish offers solid support for a variety of heavy-duty itemsPerfect storage solution for commercial or residential use in any room, office or jobsite6 fully adjustable shelves and legs help stabilize unit on uneven flooringNSF-certified for food storageNote: Product may vary by store.",
  "attributes": [
    {
      "key": "Assembled Depth (in.)",
      "value": "18 in"
    },
    {
      "key": "Assembled Height (in.)",
      "value": "72 in"
    },
    {
      "key": "Assembled Width (in.)",
      "value": "48 in"
    },
    {
      "key": "- Note",
      "value": "Product may vary by store."
    },
    {
      "key": "Durability",
      "value": "General purpose"
    },
    {
      "key": "Material",
      "value": "Wire"
    },
    {
      "key": "MFG Brand Name",
      "value": "HDX"
    },
    {
      "key": "Storage Product Type",
      "value": "Free Standing Racks and Shelves"
    }
  ],
  "isDeleted": false
}