{
  "uid": 100131,
  "name": "Leaktite Leakproof Lid for 5-Gal. Buckets",
  "description": "The 5-Gal. Homer Leakproof Lid is made of plastic material. This lid has a special design for leak resistance and contains a gasket to seal in liquid.  The Home Depot orange color is an ideal match the the 5 gallon Homer Bucket..Fits 5-gal. bucketsPlastic construction12 in. diameterResists leak",
  "attributes": [
    {
      "key": "Applicator/Tool Type",
      "value": "Bucket Lid"
    },
    {
      "key": "Material",
      "value": "Plastic"
    },
    {
      "key": "MFG Brand Name",
      "value": "Leaktite"
    },
    {
      "key": "Paint Product Type",
      "value": "Paint Buckets and Lids"
    },
    {
      "key": "Product Diameter (in.)",
      "value": "12 in"
    },
    {
      "key": "Product Weight (lb.)",
      "value": "0.62"
    }
  ],
  "isDeleted": false
}