{
  "uid": 100348,
  "name": "Hampton Bay Tropical Bamboo Reed Fence - 6ft x 16ft",
  "description": "This 6 ft. x 16 ft. natural bamboo reed fence is made for patio shading, soundproofing, duck blinds and other outdoor uses. The reeds are tightly woven with vinyl-coated, rust-resistant wire every 4 in. to help provide privacy and protection from the wind. Natural reed fences are perfect for covering unattractive chain-link fences and can create a tropical feel to your backyard or garden.Actual size is 6 ft. H x 16 ft. L (72 in. H x 192 in. L)Peeled and polished bamboo reed constructionGreat for decorating tiki bars or outdoor pool areasAttaches to existing fence posts or over an existing fenceMade from natural sustainable materialsNot recommended for over exposure to rain and snowLight weight material unrolls and rolls up easilyTransports easily",
  "attributes": [
    {
      "key": "Color Family",
      "value": "Tan"
    },
    {
      "key": "Color/Finish",
      "value": "Natural"
    },
    {
      "key": "Fence Application",
      "value": "Decorative,Garden"
    },
    {
      "key": "Garden Fencing Type",
      "value": "Reed Fence"
    },
    {
      "key": "Landscape Supply Type",
      "value": "Garden Fencing"
    },
    {
      "key": "Material",
      "value": "Bamboo"
    },
    {
      "key": "MFG Brand Name",
      "value": "Hampton Bay"
    },
    {
      "key": "Package Quantity",
      "value": "1"
    },
    {
      "key": "Product Depth (in.)",
      "value": "2"
    },
    {
      "key": "Product Height (in.)",
      "value": "192"
    },
    {
      "key": "Product Width (in.)",
      "value": "72"
    }
  ],
  "isDeleted": false
}