{
  "uid": 100523,
  "name": "JELD-WEN Premium Steel Craftsman Door - High Definition Panels",
  "description": "JELD-WEN Premium Steel doors offer that relied-upon strength, durability and ease of maintenance that complement your home\u0027s style.  Their high definition panels create an upscale look that adds architectural interest for increased curb appeal.  Our strong and secure steel doors are built to prevent water absorption and resist rust to enhance your home for many years.California residents: see\u0026nbsp;Proposition 65 informationStrong and secure steel with high definition panels for a high-end lookEnergy efficient core to help lower heating and cooling costPolystyrene core provides long-lasting insulationBrickmould (trim) is primed and ready to paintGalvanized steel resists rust and corrosionGrids are adhered to interior and exterior of glass to provide an authentic divided lite appearance that adds charm to any homeGrids are white on both interior and exterior of door2-Coats of neutral, low-sheen, baked-on enamel primer enables easier finishingPrimed doors give you the design flexibility to choose any finish colorDoor is prehung in frame for easier installationPredrilled double bore hole for lock installation (lock sold separately)From the outside, door opens into the home with hinges on the leftEasy to care for and designed to prevent water absorption and resist rustReinforced lock area provides strength and security for door hardwareCheck local building codes  before beginning your project to ensure compliancyNot all products are suitable for locations that experience severe weather",
  "attributes": [
    {
      "key": "Assembled Depth (in.)",
      "value": "5.75 in"
    },
    {
      "key": "Assembled Height (in.)",
      "value": "83 in"
    },
    {
      "key": "Assembled Width (in.)",
      "value": "40 in"
    },
    {
      "key": "Color Family",
      "value": "White"
    },
    {
      "key": "Color/Finish",
      "value": "Primed White"
    },
    {
      "key": "Commercial",
      "value": "No"
    },
    {
      "key": "Door Configuration",
      "value": "Single Door"
    },
    {
      "key": "Door Handing",
      "value": "Left-Hand/Inswing"
    },
    {
      "key": "Door Size (WxH) in.",
      "value": "36 x 80"
    },
    {
      "key": "Door Style",
      "value": "Craftsman"
    },
    {
      "key": "Door Thickness (in.)",
      "value": "1.75 in"
    },
    {
      "key": "Door Type",
      "value": "Exterior Prehung"
    },
    {
      "key": "Energy Star Qualified",
      "value": "North-Central,Northern,South-Central,Southern"
    },
    {
      "key": "Features",
      "value": "Brickmould,Weatherstripping"
    },
    {
      "key": "Finish Type",
      "value": "Primed"
    },
    {
      "key": "Fire rating",
      "value": "nan"
    },
    {
      "key": "Glass Caming Finish",
      "value": "No caming"
    },
    {
      "key": "Glass Style",
      "value": "Clear"
    },
    {
      "key": "Glass Type",
      "value": "6 Lite"
    },
    {
      "key": "Hinge Finish",
      "value": "Nickel"
    },
    {
      "key": "Included",
      "value": "No additional items or accessories included"
    },
    {
      "key": "Jamb Size (in.)",
      "value": "4-9/16\u0022"
    },
    {
      "key": "Material",
      "value": "Steel"
    },
    {
      "key": "MFG Brand Name",
      "value": "JELD-WEN"
    },
    {
      "key": "Number of Hinges",
      "value": "3"
    },
    {
      "key": "Panel Type",
      "value": "2 Panel"
    },
    {
      "key": "Product Weight (lb.)",
      "value": "90"
    },
    {
      "key": "Rough Opening Height",
      "value": "82.5 in"
    },
    {
      "key": "Rough Opening Width",
      "value": "38.5 in"
    }
  ],
  "isDeleted": false
}