{
  "uid": 100744,
  "name": "Funtime Stainless Steel Popcorn Popper",
  "description": "Entertain your friends and family, while making some of the most delicious popcorn imaginable. These beautiful classic style popcorn machines bring back the fun feel of yesteryear. Back to a time when you could buy a bag of hot buttery popcorn for a nickel.Stainless steel 4 oz. hot oil kettleSafety tempered side glass panelsBuilt-in warmer lightBuilt-in heating deck keeps popcorn hot long after it\u0027s been poppedQuality all metal constructionUnpopped kernel/old maid drawer catches unpopped kernelsProduces 2 Gal. of popcorn2 switch designBonus Accessories: Kernel Measuring Cup, Popcorn Scoop, Seasoning Shaker, Oil Measuring SpoonHome Depot Protection Plan:",
  "attributes": [
    {
      "key": "Appliance Type",
      "value": "Popcorn Popper"
    },
    {
      "key": "- Bonus Accessories",
      "value": "Kernel Measuring Cup, Popcorn Scoop, Seasoning Shaker, Oil Measuring Spoon"
    },
    {
      "key": "Certifications and Listings",
      "value": "4-UL Certified,CSA Listed,ETL Listed,NSF Listed"
    },
    {
      "key": "Color/Finish",
      "value": "Black"
    },
    {
      "key": "Color/Finish Family",
      "value": "Black"
    },
    {
      "key": "Dishwasher Safe Parts",
      "value": "No"
    },
    {
      "key": "ENERGY STAR Certified",
      "value": "No"
    },
    {
      "key": "Housing Material",
      "value": "Stainless Steel"
    },
    {
      "key": "Kernel Capacity (oz.)",
      "value": "4 oz"
    },
    {
      "key": "Locking Lid",
      "value": "No"
    },
    {
      "key": "MFG Brand Name",
      "value": "Funtime"
    },
    {
      "key": "Popper Type",
      "value": "Oil"
    },
    {
      "key": "Product Depth (in.)",
      "value": "17"
    },
    {
      "key": "Product Height (in.)",
      "value": "21"
    },
    {
      "key": "Product Weight (lb.)",
      "value": "35"
    },
    {
      "key": "Product Width (in.)",
      "value": "14"
    },
    {
      "key": "Reconditioned",
      "value": "No"
    },
    {
      "key": "Steam Vents",
      "value": "No"
    },
    {
      "key": "Voltage (volts)",
      "value": "120"
    },
    {
      "key": "Wattage (watts)",
      "value": "600"
    }
  ],
  "isDeleted": false
}