{
  "uid": 100803,
  "name": "Everbilt Hinge Pin Doorstop Kit - Satin Nickel Finish",
  "description": "The Everbilt Hinge Pin Doorstop is held in place with a hinge pin. The self-adjusting pad makes full contact with the door. An oversized bumper mounted on an adjusting screw protects the door trim.California residents: see\u0026nbsp;Proposition 65 informationSatin nickel finishAttaches to hingeNo fasteners necessaryDecorative finish to match any home decorNote: product may vary by store",
  "attributes": [
    {
      "key": "Builders Hardware Product Type",
      "value": "Door Stop"
    },
    {
      "key": "- Note",
      "value": "product may vary by store"
    },
    {
      "key": "Catch included",
      "value": "No"
    },
    {
      "key": "Door stop type",
      "value": "Hinge pin"
    },
    {
      "key": "Fasteners included",
      "value": "No"
    },
    {
      "key": "Finish",
      "value": "Satin Nickel"
    },
    {
      "key": "Hardware Finish Family",
      "value": "Nickel"
    },
    {
      "key": "Material",
      "value": "Other"
    },
    {
      "key": "MFG Brand Name",
      "value": "Everbilt"
    },
    {
      "key": "Package Quantity",
      "value": "1"
    },
    {
      "key": "Product Depth (in.)",
      "value": "2.62"
    },
    {
      "key": "Product Height (in.)",
      "value": "6.5"
    },
    {
      "key": "Product Thickness (mm)",
      "value": "2.62"
    },
    {
      "key": "Product Width (in.)",
      "value": "1.5 in"
    },
    {
      "key": "Projection",
      "value": "2.62 in"
    }
  ],
  "isDeleted": false
}