{
  "uid": 100881,
  "name": "Delta Mandara Brushed Nickel Towel Ring - EZ Clip Installation",
  "description": "Provide extra storage to your bathroom when you display the classy Delta Mandara Towel Ring in Brushed Nickel. This beautiful piece of bath hardware offers a simple base design with a glamorous feel. The brushed nickel finish gives it that sought-after touch of beauty.Brushed nickel finish complements most decorsPost is made of high-quality zinc die-cast base material ring made of steel providing long-lasting durabilityCoordinates with the Mandara faucet from DeltaFeatures the EZ clip installation method for fast, no-hassle installationMatching accessories available",
  "attributes": [
    {
      "key": "Bath Accessory Type",
      "value": "Hand Towel Holder"
    },
    {
      "key": "Color Family",
      "value": "Nickel"
    },
    {
      "key": "Color/Finish",
      "value": "Brushed Nickel"
    },
    {
      "key": "Hanger Type",
      "value": "Ring"
    },
    {
      "key": "Hardware Included",
      "value": "Yes"
    },
    {
      "key": "Material",
      "value": "Zinc"
    },
    {
      "key": "MFG Brand Name",
      "value": "Delta"
    },
    {
      "key": "Mount Type",
      "value": "Wall"
    },
    {
      "key": "Number of Hangers",
      "value": "1"
    },
    {
      "key": "Product Depth (in.)",
      "value": "3.4"
    },
    {
      "key": "Product Height (in.)",
      "value": "8.8"
    },
    {
      "key": "Product Width (in.)",
      "value": "7.6"
    },
    {
      "key": "Weight Capacity (lb.)",
      "value": "35"
    }
  ],
  "isDeleted": false
}