{
  "uid": 100961,
  "name": "Honda Gas Trimmer Pro 4-Stroke String Cutter",
  "description": "You won\u0027t find better power or performance than what you get from the Honda gas trimmer. The trimmers are highly fuel-efficient and use regular gas. That means there\u0027s no mixing of gas and oil.12.7 in. W x 10.2 in. D x 73.8 in. HEasy starting Honda GX35 cc 4-stroke engineSuperb balance, lower vibration and comfortable to use2 Year residential warrantyFlexible inner driveshaft is shock resistance and backed by a lifetime warranty360 inclinable engine that can be used and rotated in any positionHome Depot Protection Plan:",
  "attributes": [
    {
      "key": "Antivibration",
      "value": "Yes"
    },
    {
      "key": "Assembled Depth (in.)",
      "value": "10.2 in"
    },
    {
      "key": "Assembled Height (in.)",
      "value": "73.8 in"
    },
    {
      "key": "Assembled Width (in.)",
      "value": "12.7 in"
    },
    {
      "key": "Assembly Required",
      "value": "Yes"
    },
    {
      "key": "Attachment capable",
      "value": "No"
    },
    {
      "key": "CA (CARB) Compliant",
      "value": "CARB Compliant"
    },
    {
      "key": "Clutch",
      "value": "Centrifugal"
    },
    {
      "key": "Commercial",
      "value": "No"
    },
    {
      "key": "Engine Cycles",
      "value": "4 Cycle"
    },
    {
      "key": "Engine Displacement (cc)",
      "value": "35"
    },
    {
      "key": "Engine Type",
      "value": "Air Cooled, Four Stroke, Single Cylinder"
    },
    {
      "key": "Fuel tank capacity (oz.)",
      "value": "21.3"
    },
    {
      "key": "Fuel Type",
      "value": "Gasoline"
    },
    {
      "key": "Head Type",
      "value": "Fixed"
    },
    {
      "key": "Line Advance System",
      "value": "Bump"
    },
    {
      "key": "Line style size",
      "value": ".095"
    },
    {
      "key": "Maximum cutting path diameter (in.)",
      "value": "17"
    },
    {
      "key": "Metal blade conversion kit",
      "value": "No"
    },
    {
      "key": "MFG Brand Name",
      "value": "Honda"
    },
    {
      "key": "Multiple heads included",
      "value": "No"
    },
    {
      "key": "No-tool line replacement",
      "value": "Yes"
    },
    {
      "key": "Number of Trim Lines",
      "value": "2"
    },
    {
      "key": "Product Weight (lb.)",
      "value": "14.8"
    },
    {
      "key": "Recommended line diameter (in.)",
      "value": ".095"
    },
    {
      "key": "Reconditioned",
      "value": "No"
    },
    {
      "key": "Replaceable Head",
      "value": "Yes"
    },
    {
      "key": "Shaft length (in.)",
      "value": "45"
    },
    {
      "key": "Shaft shape",
      "value": "Straight"
    },
    {
      "key": "Shaft type",
      "value": "Straight"
    },
    {
      "key": "Shoulder harness/strap",
      "value": "Yes"
    },
    {
      "key": "Start Type",
      "value": "Manual"
    },
    {
      "key": "Trimmer Line Type",
      "value": "String"
    },
    {
      "key": "Trimmer Type",
      "value": "Professional Gas String"
    }
  ],
  "isDeleted": false
}